{
  "minecraft:recipes/combat/leather_helmet": {
    "criteria": {
      "has_leather": "2025-06-12 02:57:03 +0000"
    },
    "done": true
  },
  "minecraft:recipes/decorations/ladder": {
    "criteria": {
      "has_stick": "2025-06-12 02:22:53 +0000"
    },
    "done": true
  },
  "minecraft:recipes/combat/leather_leggings": {
    "criteria": {
      "has_leather": "2025-06-12 02:57:03 +0000"
    },
    "done": true
  },
  "uselessreptile:dragon/root": {
    "criteria": {
      "tick": "2025-06-12 02:16:39 +0000"
    },
    "done": true
  },
  "minecraft:recipes/decorations/oak_sign": {
    "criteria": {
      "has_planks": "2025-06-12 02:22:45 +0000"
    },
    "done": true
  },
  "minecraft:recipes/redstone/oak_trapdoor": {
    "criteria": {
      "has_planks": "2025-06-12 02:22:45 +0000"
    },
    "done": true
  },
  "wilderwild:recipes/transportation/baobab_boat": {
    "criteria": {
      "in_water": "2025-06-12 02:46:48 +0000"
    },
    "done": true
  },
  "kattersstructures:root": {
    "criteria": {
      "requirement": "2025-06-12 02:16:39 +0000"
    },
    "done": true
  },
  "minecraft:recipes/misc/bowl": {
    "criteria": {
      "has_brown_mushroom": "2025-06-12 03:02:24 +0000"
    },
    "done": true
  },
  "minecraft:recipes/tools/wooden_axe": {
    "criteria": {
      "has_stick": "2025-06-12 02:22:53 +0000"
    },
    "done": true
  },
  "minecraft:recipes/combat/leather_chestplate": {
    "criteria": {
      "has_leather": "2025-06-12 02:57:03 +0000"
    },
    "done": true
  },
  "minecraft:recipes/decorations/crafting_table": {
    "criteria": {
      "unlock_right_away": "2025-06-12 02:16:39 +0000"
    },
    "done": true
  },
  "minecraft:recipes/misc/stick": {
    "criteria": {
      "has_planks": "2025-06-12 02:22:45 +0000"
    },
    "done": true
  },
  "wilderwild:recipes/transportation/willow_boat": {
    "criteria": {
      "in_water": "2025-06-12 02:46:48 +0000"
    },
    "done": true
  },
  "wilderwild:recipes/misc/yellow_dye_from_wildflowers": {
    "criteria": {
      "has_wildflowers": "2025-06-12 02:27:44 +0000"
    },
    "done": true
  },
  "minecraft:adventure/sleep_in_bed": {
    "criteria": {
      "slept_in_bed": "2025-06-12 02:49:58 +0000"
    },
    "done": true
  },
  "minecraft:recipes/building_blocks/oak_stairs": {
    "criteria": {
      "has_planks": "2025-06-12 02:22:45 +0000"
    },
    "done": true
  },
  "minecraft:recipes/transportation/cherry_boat": {
    "criteria": {
      "in_water": "2025-06-12 02:46:48 +0000"
    },
    "done": true
  },
  "minecraft:recipes/decorations/chain": {
    "criteria": {
      "has_iron_nugget": "2025-06-12 03:00:32 +0000"
    },
    "done": true
  },
  "minecraft:recipes/decorations/oak_fence": {
    "criteria": {
      "has_planks": "2025-06-12 02:22:45 +0000"
    },
    "done": true
  },
  "minecraft:recipes/misc/red_dye_from_poppy": {
    "criteria": {
      "has_poppy": "2025-06-12 03:02:32 +0000"
    },
    "done": true
  },
  "minecraft:recipes/misc/bone_meal": {
    "criteria": {
      "has_bone": "2025-06-12 03:00:32 +0000"
    },
    "done": true
  },
  "minecraft:recipes/transportation/bamboo_raft": {
    "criteria": {
      "in_water": "2025-06-12 02:46:48 +0000"
    },
    "done": true
  },
  "minecraft:recipes/transportation/spruce_boat": {
    "criteria": {
      "in_water": "2025-06-12 02:46:48 +0000"
    },
    "done": true
  },
  "minecraft:recipes/misc/leather_horse_armor": {
    "criteria": {
      "has_leather": "2025-06-12 02:57:03 +0000"
    },
    "done": true
  },
  "minecraft:recipes/transportation/birch_boat": {
    "criteria": {
      "in_water": "2025-06-12 02:46:48 +0000"
    },
    "done": true
  },
  "minecraft:recipes/transportation/oak_boat": {
    "criteria": {
      "in_water": "2025-06-12 02:46:48 +0000"
    },
    "done": true
  },
  "minecraft:recipes/building_blocks/coal_block": {
    "criteria": {
      "has_coal": "2025-06-12 02:55:40 +0000"
    },
    "done": true
  },
  "minecraft:recipes/redstone/oak_button": {
    "criteria": {
      "has_planks": "2025-06-12 02:22:45 +0000"
    },
    "done": true
  },
  "minecraft:recipes/transportation/mangrove_boat": {
    "criteria": {
      "in_water": "2025-06-12 02:46:48 +0000"
    },
    "done": true
  },
  "wilderwild:recipes/transportation/cypress_boat": {
    "criteria": {
      "in_water": "2025-06-12 02:46:48 +0000"
    },
    "done": true
  },
  "minecraft:recipes/building_blocks/oak_slab": {
    "criteria": {
      "has_planks": "2025-06-12 02:22:45 +0000"
    },
    "done": true
  },
  "minecraft:recipes/decorations/lantern": {
    "criteria": {
      "has_iron_nugget": "2025-06-12 03:00:32 +0000"
    },
    "done": true
  },
  "wilderwild:recipes/transportation/palm_boat": {
    "criteria": {
      "in_water": "2025-06-12 02:46:48 +0000"
    },
    "done": true
  },
  "minecraft:recipes/decorations/campfire": {
    "criteria": {
      "has_stick": "2025-06-12 02:22:53 +0000"
    },
    "done": true
  },
  "minecraft:recipes/tools/wooden_hoe": {
    "criteria": {
      "has_stick": "2025-06-12 02:22:53 +0000"
    },
    "done": true
  },
  "minecraft:recipes/redstone/oak_fence_gate": {
    "criteria": {
      "has_planks": "2025-06-12 02:22:45 +0000"
    },
    "done": true
  },
  "minecraft:recipes/misc/charcoal": {
    "criteria": {
      "has_log": "2025-06-12 02:18:20 +0000"
    },
    "done": true
  },
  "minecraft:recipes/tools/wooden_pickaxe": {
    "criteria": {
      "has_stick": "2025-06-12 02:22:53 +0000"
    },
    "done": true
  },
  "minecraft:recipes/decorations/item_frame": {
    "criteria": {
      "has_leather": "2025-06-12 02:57:03 +0000"
    },
    "done": true
  },
  "minecraft:recipes/redstone/oak_pressure_plate": {
    "criteria": {
      "has_planks": "2025-06-12 02:22:45 +0000"
    },
    "done": true
  },
  "wilderwild:recipes/transportation/maple_boat": {
    "criteria": {
      "in_water": "2025-06-12 02:46:48 +0000"
    },
    "done": true
  },
  "minecraft:recipes/redstone/oak_door": {
    "criteria": {
      "has_planks": "2025-06-12 02:22:45 +0000"
    },
    "done": true
  },
  "minecraft:recipes/tools/wooden_shovel": {
    "criteria": {
      "has_stick": "2025-06-12 02:22:53 +0000"
    },
    "done": true
  },
  "minecraft:recipes/food/suspicious_stew_from_poppy": {
    "criteria": {
      "has_poppy": "2025-06-12 03:02:32 +0000"
    },
    "done": true
  },
  "minecraft:recipes/transportation/acacia_boat": {
    "criteria": {
      "in_water": "2025-06-12 02:46:48 +0000"
    },
    "done": true
  },
  "minecraft:adventure/root": {
    "criteria": {
      "killed_by_something": "2025-06-12 02:30:35 +0000"
    },
    "done": true
  },
  "minecraft:recipes/combat/wooden_sword": {
    "criteria": {
      "has_stick": "2025-06-12 02:22:53 +0000"
    },
    "done": true
  },
  "minecraft:recipes/building_blocks/oak_planks": {
    "criteria": {
      "has_logs": "2025-06-12 02:18:20 +0000"
    },
    "done": true
  },
  "minecraft:recipes/transportation/pale_oak_boat": {
    "criteria": {
      "in_water": "2025-06-12 02:46:48 +0000"
    },
    "done": true
  },
  "minecraft:adventure/adventuring_time": {
    "criteria": {
      "wilderwild:tundra": "2025-06-12 02:27:36 +0000",
      "minecraft:snowy_slopes": "2025-06-12 02:44:08 +0000",
      "minecraft:forest": "2025-06-12 02:18:24 +0000",
      "minecraft:taiga": "2025-06-12 02:16:40 +0000",
      "minecraft:grove": "2025-06-12 02:20:15 +0000",
      "minecraft:meadow": "2025-06-12 02:27:41 +0000",
      "minecraft:plains": "2025-06-12 02:24:33 +0000",
      "minecraft:jagged_peaks": "2025-06-12 02:45:18 +0000"
    },
    "done": false
  },
  "minecraft:recipes/decorations/barrel": {
    "criteria": {
      "has_planks": "2025-06-12 02:22:45 +0000"
    },
    "done": true
  },
  "minecraft:recipes/combat/leather_boots": {
    "criteria": {
      "has_leather": "2025-06-12 02:57:03 +0000"
    },
    "done": true
  },
  "wilderwild:recipes/decorations/display_lantern": {
    "criteria": {
      "has_iron_nugget": "2025-06-12 03:00:32 +0000"
    },
    "done": true
  },
  "minecraft:recipes/food/mushroom_stew": {
    "criteria": {
      "has_brown_mushroom": "2025-06-12 03:02:24 +0000"
    },
    "done": true
  },
  "minecraft:recipes/building_blocks/oak_wood": {
    "criteria": {
      "has_log": "2025-06-12 02:18:20 +0000"
    },
    "done": true
  },
  "minecraft:story/root": {
    "criteria": {
      "crafting_table": "2025-06-12 02:22:53 +0000"
    },
    "done": true
  },
  "minecraft:recipes/misc/iron_ingot_from_nuggets": {
    "criteria": {
      "has_iron_nugget": "2025-06-12 03:00:32 +0000"
    },
    "done": true
  },
  "minecraft:recipes/transportation/jungle_boat": {
    "criteria": {
      "in_water": "2025-06-12 02:46:48 +0000"
    },
    "done": true
  },
  "minecraft:recipes/transportation/dark_oak_boat": {
    "criteria": {
      "in_water": "2025-06-12 02:46:48 +0000"
    },
    "done": true
  },
  "DataVersion": 4189
}